<?xml version="1.0" encoding="UTF-8"?>
<!DOCTYPE rules SYSTEM "https://resources.jetbrains.com/writerside/1.0/redirection-rules.dtd">
<rules>
    <!-- format is as follows
    <rule id="<unique id>">
        <accepts>page.html</accepts>
    </rule>
    -->
    <rule id="4b9a837d">
        <description>Created after removal of "About lms" from lms</description>
        <accepts>starter-topic.html</accepts>
    </rule>
    <rule id="2ecdf9a0">
        <description>Created after removal of "Input and Response schemas of API endpoints" from Hübner Kft. Lifecycle
            Management System
        </description>
        <accepts>Schemas.html</accepts>
    </rule>
</rules>